CHANGES.rst
CONTRIBUTORS.rst
MANIFEST.in
README.rst
setup.py
docs/LICENSE.GPL
docs/LICENSE.txt
docs/logo-comune-pd-150x200.jpg
pd/__init__.py
pd.prenotazioni.egg-info/PKG-INFO
pd.prenotazioni.egg-info/SOURCES.txt
pd.prenotazioni.egg-info/dependency_links.txt
pd.prenotazioni.egg-info/entry_points.txt
pd.prenotazioni.egg-info/namespace_packages.txt
pd.prenotazioni.egg-info/not-zip-safe
pd.prenotazioni.egg-info/requires.txt
pd.prenotazioni.egg-info/top_level.txt
pd/prenotazioni/README.rst
pd/prenotazioni/__init__.py
pd/prenotazioni/config.py
pd/prenotazioni/configure.zcml
pd/prenotazioni/extender.py
pd/prenotazioni/i18n.sh
pd/prenotazioni/monkey.py
pd/prenotazioni/monkey.zcml
pd/prenotazioni/testing.py
pd/prenotazioni/EXTENSIONS/install.py
pd/prenotazioni/actions/__init__.py
pd/prenotazioni/actions/configure.zcml
pd/prenotazioni/actions/mail.py
pd/prenotazioni/browser/__init__.py
pd/prenotazioni/browser/configure.zcml
pd/prenotazioni/browser/contentrules_patch.py
pd/prenotazioni/browser/foldercontents.py
pd/prenotazioni/browser/interfaces.py
pd/prenotazioni/browser/prenotazione_add.py
pd/prenotazioni/browser/prenotazione_confirm.pt
pd/prenotazioni/browser/prenotazione_print.py
pd/prenotazioni/browser/prenotazione_print_pdf.pt
pd/prenotazioni/browser/prenotazione_print_pdf.py
pd/prenotazioni/browser/prenotazione_tooltip.pt
pd/prenotazioni/browser/prenotazioni_context_state.py
pd/prenotazioni/browser/prenotazioni_search.pt
pd/prenotazioni/browser/prenotazioni_search.py
pd/prenotazioni/browser/static/backend.js
pd/prenotazioni/browser/static/jquery.tooltipster.min.js
pd/prenotazioni/browser/static/tooltipster.css
pd/prenotazioni/browser/stats/__init__.py
pd/prenotazioni/browser/stats/booking_stats.pt
pd/prenotazioni/browser/stats/booking_stats.py
pd/prenotazioni/browser/stats/booking_stats_admin.pt
pd/prenotazioni/browser/stats/booking_stats_delete.py
pd/prenotazioni/browser/stats/configure.zcml
pd/prenotazioni/browser/widgets/__init__.py
pd/prenotazioni/browser/widgets/configure.zcml
pd/prenotazioni/browser/widgets/same_day_booking_disallowed.pt
pd/prenotazioni/browser/widgets/same_day_booking_disallowed.py
pd/prenotazioni/events/__init__.py
pd/prenotazioni/events/configure.zcml
pd/prenotazioni/events/events_logger.py
pd/prenotazioni/indexers/__init__.py
