Metadata-Version: 2.1
Name: pd.prenotazioni
Version: 1.6.0
Summary: pd.prenotazioni: a Plone product for booking
Home-page: http://svn.plone.org/svn/collective/
Author: RedTurtle Technology
Author-email: sviluppoplone@redturtle.it
License: gpl
Platform: UNKNOWN
Classifier: Framework :: Plone
Classifier: Intended Audience :: Developers
Provides-Extra: test
